odoo/addons/portal_sale_personal_data_only/README.rst
odoo/addons/portal_sale_personal_data_only/__init__.py
odoo/addons/portal_sale_personal_data_only/__manifest__.py
odoo/addons/portal_sale_personal_data_only/hooks.py
odoo/addons/portal_sale_personal_data_only/i18n/de.po
odoo/addons/portal_sale_personal_data_only/i18n/es.po
odoo/addons/portal_sale_personal_data_only/i18n/it.po
odoo/addons/portal_sale_personal_data_only/i18n/portal_sale_personal_data_only.pot
odoo/addons/portal_sale_personal_data_only/i18n/zh_CN.po
odoo/addons/portal_sale_personal_data_only/readme/CONTRIBUTORS.md
odoo/addons/portal_sale_personal_data_only/readme/DESCRIPTION.md
odoo/addons/portal_sale_personal_data_only/readme/USAGE.md
odoo/addons/portal_sale_personal_data_only/security/security.xml
odoo/addons/portal_sale_personal_data_only/static/description/icon.png
odoo/addons/portal_sale_personal_data_only/static/description/index.html
odoo/addons/portal_sale_personal_data_only/tests/__init__.py
odoo/addons/portal_sale_personal_data_only/tests/test_partner_access.py
odoo_addon_portal_sale_personal_data_only-18.0.1.0.0.2.dist-info/METADATA
odoo_addon_portal_sale_personal_data_only-18.0.1.0.0.2.dist-info/WHEEL
odoo_addon_portal_sale_personal_data_only-18.0.1.0.0.2.dist-info/top_level.txt
odoo_addon_portal_sale_personal_data_only-18.0.1.0.0.2.dist-info/RECORD
